Workbook

Sheet Партнёры
A1: ID | B1: Блок | C1: Организация (EN) | D1: Название (местн.) | E1: Страна | F1: Город | G1: Тип партнёра | H1: Приоритет | I1: Что просить | J1: Контакт (e-mail) | K1: Сайт | L1: Карточка (файл) | M1: Статус | N1: Дата отправки | O1: Комментарий
A2: CN-01 | B2: Китай | C2: China Association for Science and Technology (CAST) - Dept of International Cooperation | D2: 中国科学技术协会 国际合作部 | E2: China | F2: Beijing | G2: Госорг./популяризация | H2: HIGH | I2: Включить Узбекистан/TPM в международный тур China Mobile S&T Museum; стажировка 2 сотрудников | J2: fengkai@cast.org.cn | K2: https://cast.org.cn | L2: 01-china.md
A3: CN-02 | B3: Китай | C3: China Science and Technology Museum (CSTM) - China Mobile S&T Museum | D3: 中国科学技术馆 / 中国流动科技馆 | E3: China | F3: Beijing | G3: Передвижные выставки | H3: HIGH | I3: Тур в TPM на 3 года (60 экспонатов + купол); технический паспорт | J3: не опубликован — см. карточку | K3: https://cstm.cdstm.cn | L3: 01-china.md
A4: CN-03 | B4: Китай | C4: China Association of Natural Science Museums (CANSM) / BRISMIS | D4: 中国自然科学博物馆学会 | E4: China | F4: Beijing | G4: Сеть/ассоциация | H4: HIGH | I4: Приглашение на BRISMIS; партнёрство/членство | J4: не опубликован — см. карточку | K4: https://cansm.org.cn | L4: 01-china.md
A5: CN-17 | B5: Китай | C5: Hefei Panshi Intelligent Technology | D5: 合肥磐石智能科技 | E5: China | F5: Hefei | G5: Производитель (покупка) | H5: HIGH | I5: Прайс на 10 физических станций + модуль транспорт/энергия | J5: panshizhineng@outlook.com | K5: https://panshiexhibit.com | L5: 01-china.md
A6: CN-19 | B6: Китай | C6: UBTECH Robotics | D6: 优必选科技 | E6: China | F6: Shenzhen | G6: Производитель (покупка), Спонсор/донор | H6: HIGH | I6: Робот-зона: наборы + демо-гуманоид; спонсорские условия | J6: UBTECH.EDU@ubtrobot.com | K6: https://ubtrobot.com | L6: 01-china.md
A7: RU-01 | B7: Россия | C7: Polytechnic Museum (Moscow) | D7: Политехнический музей | E7: Russia | F7: Moscow | G7: Отраслевой музей, Передвижные выставки, Сеть/ассоциация | H7: HIGH | I7: Реализация соглашения 2024: перекрёстная выставка, стажировки, реставрация | J7: info@polytech.one | K7: https://polymus.ru | L7: 03-russia.md
A8: RU-02 | B8: Россия | C8: NAUKA 0+ International Science Festival (Festival Directorate; MSU; Ministry of Science RF) | D8: Фестиваль NAUKA 0+ | E8: Russia | F8: Moscow/Tashkent | G8: Госорг./популяризация | H8: HIGH | I8: TPM — постоянный соорганизатор; выставочный блок; форум организаторов | J8: e.fayzullina@festivalnauki.ru | K8: https://festivalnauki.ru | L8: 03-russia.md
A9: RU-04 | B9: Россия | C9: EXPONI Group | D9: ГК ЭКСПОНИ | E9: Russia | F9: Moscow (Zelenograd) | G9: Производитель (покупка) | H9: HIGH | I9: КП на 10 станций + модуль «Автомобиль изнутри» | J9: info@exponi.ru | K9: https://exponi.ru | L9: 03-russia.md
A10: RU-05 | B10: Россия | C10: Einsteinarium | D10: Эйнштейнариум | E10: Russia | F10: — | G10: Производитель (покупка) | H10: HIGH | I10: КП на мобильную школьную выставку 20–30 экспонатов | J10: Einsteinarium36@gmail.com | K10: https://einsteinarium.ru | L10: 03-russia.md
A11: TR-01 | B11: Турция | C11: Turkish Technology Team Foundation (T3) - Bilim Türkiye / DENEYAP / TEKNOFEST | D11: Türkiye Teknoloji Takımı Vakfı | E11: Turkey | F11: Istanbul | G11: Госорг./популяризация, Передвижные выставки | H11: HIGH | I11: Партнёрство с Bilim Taşkent; мастерские DENEYAP в TPM; TEKNOFEST | J11: bilimturkiye@turkiyeteknolojitakimi.org | K11: https://t3vakfi.org | L11: 03-turkey.md
A12: TR-03 | B12: Турция | C12: TİKA - Tashkent Program Coordination Office | D12: TİKA Taşkent Program Koordinasyon Ofisi | E12: Uzbekistan (Turkish agency) | F12: Tashkent | G12: Госорг./популяризация, Спонсор/донор | H12: HIGH | I12: Грант на мейкер-мастерскую/интерактивный модуль | J12: taskent@tika.gov.tr | K12: https://tika.gov.tr | L12: 03-turkey.md
A13: DE-07 | B13: Германия | C13: Ecsite — European Network of Science Centres and Museums | D13: Ecsite | E13: Belgium (EU network) | F13: Brussels | G13: Сеть/ассоциация | H13: HIGH | I13: Associate-членство TPM | J13: members@ecsite.eu | K13: https://ecsite.eu | L13: 03-germany.md
... A57: CN-11 | B57: Китай | C57: Shanghai Auto Museum | D57: 上海汽车博物馆 | E57: China | F57: Shanghai | G57: Отраслевой музей | H57: LOW | I57: Консультации по автозалу; совместная выставка | J57: Info@shautomuseum.com | K57: https://shautomuseum.com | L57: 01-china.md
A58: CN-12 | B58: Китай | C58: Beijing Auto Museum | D58: 北京汽车博物馆 | E58: China | F58: Beijing | G58: Отраслевой музей | H58: LOW | I58: Совместная выставка; консультации | J58: не опубликован — см. карточку | L58: 01-china.md
A59: CN-13 | B59: Китай | C59: China Railway Museum | D59: 中国铁道博物馆 | E59: China | F59: Beijing | G59: Отраслевой музей | H59: LOW | I59: Консультации по ж/д экспозиции | J59: не опубликован — см. карточку | L59: 01-china.md
A60: CN-14 | B60: Китай | C60: Beihang Aviation and Aerospace Museum | D60: 北京航空航天博物馆 | E60: China | F60: Beijing | G60: Отраслевой музей | H60: LOW | I60: Консультации по авиаэкспозиции; образовательные программы | J60: international@buaa.edu.cn | K60: https://buaa.edu.cn | L60: 01-china.md
A61: CN-15 | B61: Китай | C61: Macao Grand Prix Museum | D61: 澳門大賽車博物館 | E61: China (Macao SAR) | F61: Macao | G61: Отраслевой музей | H61: LOW | I61: Консультации по симуляторам/разрезам | J61: mgpm@macaotourism.gov.mo | K61: https://mgpm.macaotourism.gov.mo | L61: 01-china.md
A62: CN-16 | B62: Китай | C62: Tianjin Science and Technology Museum | D62: 天津科学技术馆 | E62: China | F62: Tianjin | G62: Передвижные выставки | H62: LOW | I62: Обмен выставками (побратимы Тяньцзинь—Ташкент) | J62: не опубликован — см. карточку | K62: https://tjstm.org | L62: 01-china.md
A63: CN-18 | B63: Китай | C63: QINGCHUANG (Zigong Qingchuang Technology) | D63: 自贡青创科技 | E63: China | F63: Zigong | G63: Производитель (покупка) | H63: LOW | I63: Сравнительный прайс | J63: не опубликован — см. карточку | K63: https://interactiveexhibit.com | L63: 01-china.md
A64: RU-07 | B64: Россия | C64: Russian Railway Museum (RZD) | D64: Музей железных дорог России | E64: Russia | F64: St Petersburg | G64: Отраслевой музей | H64: LOW | I64: Консультации; выставка «Колея 1520» | J64: info@rzd-museum.ru | K64: https://rzd-museum.ru | L64: 03-russia.md
A65: RU-08 | B65: Россия | C65: Moscow Transport Museum | D65: Музей Транспорта Москвы | E65: Russia | F65: Moscow | G65: Отраслевой музей | H65: LOW | I65: Партнёрская выставка о городском транспорте | J65: partners@mtmuseum.ru | K65: https://mtmuseum.ru | L65: 03-russia.md
A66: TR-04 | B66: Турция | C66: Rahmi M. Koç Museum | D66: Rahmi M. Koç Müzesi | E66: Turkey | F66: Istanbul | G66: Отраслевой музей | H66: LOW | I66: Консультации по реставрации авто; стажировка; обмен выставками | J66: msofuoglu@rmk-museum.org.tr | K66: https://rmk-museum.org.tr | L66: 03-turkey.md
A67: TR-06 | B67: Турция | C67: Konya Science Centre | D67: Konya Bilim Merkezi | E67: Turkey | F67: Konya | G67: Передвижные выставки | H67: LOW | I67: Обмен методиками; стажировка | J67: bilgi@kbm.org.tr | K67: https://kbm.org.tr | L67: 03-turkey.md
A68: DE-03 | B68: Германия | C68: Max Planck Society — Science Tunnel | D68: Max-Planck-Gesellschaft | E68: Germany | F68: Munich | G68: Передвижные выставки | H68: LOW | I68: Условия показа новой версии Science Tunnel | J68: не опубликован — см. карточку | K68: https://mpg.de | L68: 03-germany.md
A69: DE-06 | B69: Германия | C69: Deutscher Museumsbund | D69: Deutscher Museumsbund | E69: Germany | F69: Berlin | G69: Передача снятых экспонатов, Сеть/ассоциация | H69: LOW | I69: Доступ к базе предметов на вывод для зарубежного музея | J69: office@museumsbund.de | K69: https://museumsbund.de | L69: 03-germany.md
A70: DE-09 | B70: Германия | C70: iMOVE (BIBB) | D70: iMOVE | E70: Germany | F70: Bonn | G70: Госорг./популяризация | H70: LOW | I70: Немецкие поставщики учебных стендов | J70: не опубликован — см. карточку | K70: https://imove-germany.de | L70: 03-germany.md
A71: UK-04 | B71: Великобритания | C71: University of Westminster / WIUT | D71: WIUT | E71: Uzbekistan/UK | F71: Tashkent | G71: Госорг./популяризация | H71: LOW | I71: STEM-мероприятия, студенты-волонтёры | J71: не опубликован — см. карточку | K71: https://westminster.ac.uk | L71: 03-uk.md
... A80: IT-10 | B80: Италия | C80: Fondazione FS Italiane — Pietrarsa Railway Museum | D80: Fondazione FS Italiane | E80: Italy | F80: Rome/Naples | G80: Отраслевой музей | H80: LOW | I80: Консультации; ж/д мультимедийная выставка | J80: museopietrarsa@fondazionefs.it | K80: https://fondazionefs.it | L80: 03-italy.md

Sheet Сводка
A1: Блок | B1: HIGH | C1: MEDIUM | D1: LOW | E1: Всего | G1: Статусы (лист «Партнёры», колонка M)
A2: Китай | B2: =COUNTIFS(Партнёры!$B$2:$B$80,$A2,Партнёры!$H$2:$H$80,B$1) | C2: =COUNTIFS(Партнёры!$B$2:$B$80,$A2,Партнёры!$H$2:$H$80,C$1) | D2: =COUNTIFS(Партнёры!$B$2:$B$80,$A2,Партнёры!$H$2:$H$80,D$1) | E2: =SUM(B2:D2) | G2: отправлено | H2: =COUNTIF(Партнёры!$M$2:$M$80,G2)
A3: Россия | B3: =COUNTIFS(Партнёры!$B$2:$B$80,$A3,Партнёры!$H$2:$H$80,B$1) | C3: =COUNTIFS(Партнёры!$B$2:$B$80,$A3,Партнёры!$H$2:$H$80,C$1) | D3: =COUNTIFS(Партнёры!$B$2:$B$80,$A3,Партнёры!$H$2:$H$80,D$1) | E3: =SUM(B3:D3) | G3: ответили | H3: =COUNTIF(Партнёры!$M$2:$M$80,G3)
A4: Турция | B4: =COUNTIFS(Партнёры!$B$2:$B$80,$A4,Партнёры!$H$2:$H$80,B$1) | C4: =COUNTIFS(Партнёры!$B$2:$B$80,$A4,Партнёры!$H$2:$H$80,C$1) | D4: =COUNTIFS(Партнёры!$B$2:$B$80,$A4,Партнёры!$H$2:$H$80,D$1) | E4: =SUM(B4:D4) | G4: в переговорах | H4: =COUNTIF(Партнёры!$M$2:$M$80,G4)
A5: Германия | B5: =COUNTIFS(Партнёры!$B$2:$B$80,$A5,Партнёры!$H$2:$H$80,B$1) | C5: =COUNTIFS(Партнёры!$B$2:$B$80,$A5,Партнёры!$H$2:$H$80,C$1) | D5: =COUNTIFS(Партнёры!$B$2:$B$80,$A5,Партнёры!$H$2:$H$80,D$1) | E5: =SUM(B5:D5) | G5: отказ | H5: =COUNTIF(Партнёры!$M$2:$M$80,G5)
A6: Великобритания | B6: =COUNTIFS(Партнёры!$B$2:$B$80,$A6,Партнёры!$H$2:$H$80,B$1) | C6: =COUNTIFS(Партнёры!$B$2:$B$80,$A6,Партнёры!$H$2:$H$80,C$1) | D6: =COUNTIFS(Партнёры!$B$2:$B$80,$A6,Партнёры!$H$2:$H$80,D$1) | E6: =SUM(B6:D6)
A7: Италия | B7: =COUNTIFS(Партнёры!$B$2:$B$80,$A7,Партнёры!$H$2:$H$80,B$1) | C7: =COUNTIFS(Партнёры!$B$2:$B$80,$A7,Партнёры!$H$2:$H$80,C$1) | D7: =COUNTIFS(Партнёры!$B$2:$B$80,$A7,Партнёры!$H$2:$H$80,D$1) | E7: =SUM(B7:D7)
A8: Итого | B8: =SUM(B2:B7) | C8: =SUM(C2:C7) | D8: =SUM(D2:D7) | E8: =SUM(E2:E7)
A11: Подсказка: заполняйте жёлтые колонки M–O на листе «Партнёры» (статус: отправлено / ответили / в переговорах / отказ) — сводка пересчитается.

Sheet Рейтинг стран
A1: Ранг | B1: Страна | C1: Баллы (К1–К6) | D1: Итог | E1: Выполнены (2) / частично (1) | F1: Лучшие 3 партнёра
A2: спр. | B2: Китай (этап 1) | C2: 2-2-2-1-2-2 = 11 | D2: HIGH | E2: К1, К2, К3, К5, К6 / К4 | F2: CAST + CSTM (тур), CANSM/BRISMIS, Panshi
A3: 1 | B3: Россия | C3: 2-2-2-1-2-1 = 10 | D3: HIGH | E3: К1, К2, К3, К5 / К4, К6 | F3: Политехнический музей (Москва); Росатом (ИЦАТ в Ташкенте); Трансмашхолдинг
A4: 2 | B4: Турция | C4: 2-2-2-1-2-1 = 10 | D4: HIGH | E4: К1, К2, К3, К5 / К4, К6 | F4: Фонд T3 (Bilim Taşkent); TÜBİTAK (научные центры, программа 2518); Rahmi M. Koç Museum
A5: 3 | B5: Германия | C5: 2-2-2-1-1-2 = 10 | D5: HIGH | E5: К1, К2, К3, К6 / К4, К5 | F5: Max Planck Society / archimedes exhibitions (Science Tunnel); Deutsches Museum; MAN Truck & Bus (СП с «Узавтосаноатом»)
A6: 4 | B6: Великобритания | C6: 2-2-2-0-1-2 = 9 | D6: HIGH | E6: К1, К2, К3, К6 / К5 | F6: Science Museum Group (туры, консалтинг); 1001 Inventions; British Council Uzbekistan
A7: 5 | B7: Италия | C7: 1-2-2-0-1-2 = 8 | D7: MEDIUM | E7: К2, К3, К6 / К1, К5 | F7: Turin Polytechnic University in Tashkent / Politecnico di Torino; Museo Nazionale Scienza e Tecnologia; Leonardo3
A8: 6 | B8: Франция | C8: 2-1-2-0-1-2 = 8 | D8: MEDIUM | E8: К1, К3, К6 / К2, К5 | F8: Universcience (Cité des sciences); Orano; Musée des Arts et Métiers
A9: 7 | B9: Южная Корея | C9: 1-2-2-0-1-1 = 7 | D9: MEDIUM | E9: К2, К3 / К1, К5, К6 | F9: Hyundai Rotem; Kia (через ADM Jizzakh); KOICA
A10: 8 | B10: Япония | C10: 1-2-2-1-0-1 = 7 | D10: MEDIUM | E10: К2, К3 / К1, К4, К6 | F10: JST (Sakura Science); JICA; Miraikan
A11: 9 | B11: Финляндия | C11: 2-0-1-1-1-2 = 7 | D11: MEDIUM | E11: К1, К6 / К3, К4, К5 | F11: Heureka Overseas Productions; — ; —
A12: 10 | B12: Индия | C12: 2-2-1-0-1-0 = 6 | D12: MEDIUM | E12: К1, К2 / К3, К5 | F12: NCSM; ITEC (MEA); —
... A29: 27 | B29: Катар | C29: 0-0-0-0-1-0 = 1 | D29: LOW | E29: — / К5 | F29: Unknown — further research required

Sheet План — первые 10 писем
A1: # | B1: Кому | C1: ID | D1: Канал | E1: Что просим | F1: Почему в первой десятке
A2: 1 | B2: Дирекция фестиваля NAUKA 0+ (Э. Файзуллина) | C2: RU-02 | D2: Прямой e-mail | E2: TPM — постоянный соорганизатор фестиваля на 2027–2028 + выставочный блок | F2: TPM уже три года центральная площадка фестиваля, нужно лишь оформить партнёрство
A3: 2 | B3: Политехнический музей (Москва) | C3: RU-01 | D3: Прямой e-mail + копия в посольство Узбекистана в РФ | E3: План на 2027 по соглашению 2024 г.: перекрёстная выставка, стажировки | F3: Соглашение об обмене экспонатами уже подписано (сначала проверить, с TPM ли)
A4: 3 | B4: CAST (Ms. Feng Kai) | C4: CN-01 | D4: Официальное письмо через посольство Узбекистана в КНР + e-mail | E4: Тур «China Mobile S&T Museum» в Ташкент на 3 года | F4: Самая крупная бесплатная/софинансируемая выставка (60 экспонатов)
A5: 4 | B5: BYD Uzbekistan Factory (Ш. Алимов) | C5: CN-22 | D5: Письмо через «Узавтосаноат» (акционер СП и учредитель TPM) | E5: Разрезной электромобиль, стенд батареи | F5: Внутренний канал учредителя, быстрая сделка
A6: 5 | B6: MAN Auto-Uzbekistan | C6: DE-01 | D6: Через «Узавтосаноат» | E6: Разрез двигателя/КПП грузовика | F6: Тот же внутренний канал
A7: 6 | B7: TİKA Ташкент | C7: TR-03 | D7: Встреча в офисе + проектная заявка | E7: Грант на мейкер-мастерскую | F7: Офис в Ташкенте, финансирует оснащение
A8: 7 | B8: Фонд T3 (Bilim Türkiye) | C8: TR-01 | D8: E-mail + встреча с Агентством по делам молодёжи Узбекистана | E8: Партнёрство с Bilim Taşkent | F8: Проект уже согласован в Ташкенте
A9: 8 | B9: 1001 Inventions | C9: UK-01 | D9: E-mail + через Центр исламской цивилизации | E9: Совместный школьный маршрут; аренда выставок | F9: Уже работают в Ташкенте (детский музей открыт 01.06.2026)
A10: 9 | B10: Ecsite | C10: DE-07 | D10: Онлайн-заявка + members@ecsite.eu | E10: Associate-членство | F10: Вход в главную сеть научных музеев, недорого
A11: 10 | B11: Science Museum Group (Touring) | C11: UK-02 | D11: E-mail | E11: Brochure 2026 + цена blueprint-пакета | F11: Выставка мирового уровня без расходов на перевозку

Sheet Легенда
A1: Поле | B1: Значение
A2: Приоритет HIGH | B2: Есть международная программа, закрывает профиль TPM, контакт опубликован, есть прецедент (ЦА/СНГ/«Пояс и путь»)
A3: Приоритет MEDIUM | B3: Не хватает одного из условий
A4: Приоритет LOW | B4: Не хватает двух и более условий
A5: Типы партнёров | B5: см. ниже
A6: Тип 1 | B6: Сеть/ассоциация
A7: Тип 2 | B7: Передвижные выставки
A8: Тип 3 | B8: Госорг./популяризация
A9: Тип 4 | B9: Передача снятых экспонатов
A10: Тип 5 | B10: Производитель (покупка)
A11: Тип 6 | B11: Спонсор/донор
A12: Тип 7 | B12: Отраслевой музей
... A15: Важно | B15: E-mail проверялись через поисковую выдачу — перед отправкой сверить на странице-источнике
